sentry_auth_crowd/__init__.py
sentry_auth_crowd/backend.py
sentry_auth_crowd/constants.py
sentry_auth_crowd-0.6.0.dist-info/DESCRIPTION.rst
sentry_auth_crowd-0.6.0.dist-info/METADATA
sentry_auth_crowd-0.6.0.dist-info/RECORD
sentry_auth_crowd-0.6.0.dist-info/WHEEL
sentry_auth_crowd-0.6.0.dist-info/metadata.json
sentry_auth_crowd-0.6.0.dist-info/top_level.txt
