Metadata-Version: 2.0
Name: sentry-auth-crowd
Version: 0.6.0
Summary: Crowd authentication provider for Sentry
Home-page: https://github.com/trbs/sentry-auth-crowd
Author: Bas van Oostveen
Author-email: trbs@trbs.net
License: Apache 2.0
Platform: UNKNOWN
Classifier: Intended Audience :: Developers
Classifier: Intended Audience :: System Administrators
Classifier: Operating System :: OS Independent
Classifier: Topic :: Software Development
Requires-Dist: Crowd (>=1.0.1)
Requires-Dist: sentry (>=8.10.0)
Provides-Extra: tests
Requires-Dist: flake8 (<2.1,>=2.0); extra == 'tests'
